Workbook

Sheet Index
B1: Google Sheets Essentials
B2: Advanced Functions & Formula Combinations
B4: LINK | C4: TOPIC | E4: COMPREHENSION | F4: YOUR NOTES
B5: LINK | C5: INDEX MATCH for Complex Lookups | E5: Select One…
B6: LINK | C6: Challenge: Find the Mistake! Index Match Problem | E6: Select One…
B7: LINK | C7: INDEX MATCH with Multiple Headers (Pro Tip) | E7: Select One…
B8: LINK | C8: Array Formulas & Functions | E8: Select One…
B9: LINK | C9: INDIRECT Function: Lookup from Different Sheets | E9: Select One…
B10: LINK | C10: Generate Random Data & Text (RANDBETWEEN) | E10: Select One…
B11: LINK | C11: The Power of SEQUENCE Function (Dynamic Yearly Calendar) | E11: Select One…

Sheet IndexMatch
A1: Index Match for Complex Lookups
A3: Sales by Product Group
B4: January | C4: February | D4: March | E4: April | F4: May | G4: June | J4: June
A5: Laptop | B5: 9150 | C5: 8750 | D5: 6840 | E5: 6200 | F5: 4220 | G5: 6800 | I5: Men | J5: {=index(B5:G9,match(I5,A5:A9,0),match(J4,B4:G4,0))} -> 3080
A6: Phone Case | B6: 10020 | C6: 6220 | D6: 9260 | E6: 9900 | F6: 4230 | G6: 16900
A7: Women | B7: 17500 | C7: 15000 | D7: 15800 | E7: 8500 | F7: 4800 | G7: 16680
A8: Men | B8: 6620 | C8: 6860 | D8: 6050 | E8: 6070 | F8: 6900 | G8: 3080
A9: Unisex | B9: 550 | C9: 450 | D9: 420 | E9: 350 | F9: 610 | G9: 540
A12: January | B12: February | C12: March | D12: April | E12: May | F12: June | G12: Products | J12: February
A13: 9150 | B13: 8750 | C13: 6840 | D13: 6200 | E13: 4220 | F13: 6800 | G13: Laptop | I13: Men | J13: {=index(A13:F17,match(I13,G13:G17,0),match(J12,A12:F12,0))} -> 6860
A14: 10020 | B14: 6220 | C14: 9260 | D14: 9900 | E14: 4230 | F14: 16900 | G14: Phone Case
A15: 17500 | B15: 15000 | C15: 15800 | D15: 8500 | E15: 4800 | F15: 16680 | G15: Women
A16: 6620 | B16: 6860 | C16: 6050 | D16: 6070 | E16: 6900 | F16: 3080 | G16: Men
A17: 550 | B17: 450 | C17: 420 | D17: 350 | E17: 610 | F17: 540 | G17: Unisex

Sheet Challenge IndexMatch
A1: Find the Mistake: INDEX MATCH | L1: -->
A2: 1. The formulas in J7 to J9 are wrong! They return the incorrect values. Find the mistake and correct them.
A3: 2. Find the Bonus % (column Q) for each employee. The lookup table is in U:W.
N5: Full name | O5: Start Date | P5: Salary | Q5: Bonus % | U5: Bonus % | V5: Comment | W5: Name
A6: January | B6: February | C6: March | D6: April | E6: May | F6: June | G6: Product | J6: February | N6: Walter Miller | O6: 43845 | P6: 25709 | Q6: =ifna(index($U$6:$U$19,match(N6,$W$6:$W$19,0)),"") -> 0.1 | S6: =ifna(HLOOKUP(N6,AdvancedIndex!$X$5:$AA$7,3,false),"") | U6: 0.3 | V6: Increased from 10% | W6: Matilda Parry
A7: 9150 | B7: 8750 | C7: 6840 | D7: 6200 | E7: 4220 | F7: 6800 | G7: Laptop | I7: Women | J7: =index($A$7:$F$11,match(I7,$G$7:$G$11,0),match($J$6,$A$6:$F$6,0)) -> 15000 | N7: Kim West | O7: 43132 | P7: 26500 | Q7: =ifna(index($U$6:$U$19,match(N7,$W$6:$W$19,0)),"") -> 0.25 | S7: =ifna(HLOOKUP(N7,AdvancedIndex!$X$5:$AA$7,3,false),"") | U7: 0.3 | W7: Robert Blume
A8: 10020 | B8: 6220 | C8: 9260 | D8: 9900 | E8: 4230 | F8: 16900 | G8: Phone Case | I8: Men | J8: =index($A$7:$F$11,match(I8,$G$7:$G$11,0),match($J$6,$A$6:$F$6,0)) -> 6860 | N8: Lyric Wise | O8: 43214 | P8: 24200 | Q8: =ifna(index($U$6:$U$19,match(N8,$W$6:$W$19,0)),"") | S8: =ifna(HLOOKUP(N8,AdvancedIndex!$X$5:$AA$7,3,false),"") | U8: 0.3 | W8: Brigitte Bond
A9: 17500 | B9: 15000 | C9: 15800 | D9: 8500 | E9: 4800 | F9: 16680 | G9: Women | I9: Laptop | J9: =index($A$7:$F$11,match(I9,$G$7:$G$11,0),match($J$6,$A$6:$F$6,0)) -> 8750 | N9: Vanessa Chavez | O9: 43068 | P9: 30600 | Q9: =ifna(index($U$6:$U$19,match(N9,$W$6:$W$19,0)),"") | S9: =ifna(HLOOKUP(N9,AdvancedIndex!$X$5:$AA$7,3,false),"") | U9: 0.25 | V9: Increase as of Feb | W9: Kim West
A10: 6620 | B10: 6860 | C10: 6050 | D10: 6070 | E10: 6900 | F10: 3080 | G10: Men | N10: Reid Good | O10: 42808 | P10: 31900 | Q10: =ifna(index($U$6:$U$19,match(N10,$W$6:$W$19,0)),"") -> 0.25 | S10: =ifna(HLOOKUP(N10,AdvancedIndex!$X$5:$AA$7,3,false),"") | U10: 0.25 | W10: Reid Good
A11: 550 | B11: 450 | C11: 420 | D11: 350 | E11: 610 | F11: 540 | G11: Unisex | N11: Christopher Sharp | O11: 42604 | P11: 32500 | Q11: =ifna(index($U$6:$U$19,match(N11,$W$6:$W$19,0)),"") | S11: =ifna(HLOOKUP(N11,AdvancedIndex!$X$5:$AA$7,3,false),"") | U11: 0.25 | W11: Robert Hurley
N12: Jessica Lowe | O12: 42746 | P12: 32800 | Q12: =ifna(index($U$6:$U$19,match(N12,$W$6:$W$19,0)),"") | S12: =ifna(HLOOKUP(N12,AdvancedIndex!$X$5:$AA$7,3,false),"") | U12: 0.2 | W12: Makai Bond
N13: Evie Williamson | O13: 42724 | P13: 25900 | Q13: =ifna(index($U$6:$U$19,match(N13,$W$6:$W$19,0)),"") | S13: =ifna(HLOOKUP(N13,AdvancedIndex!$X$5:$AA$7,3,false),"") | U13: 0.2 | W13: Kristina Mclean
N14: Matilda Parry | O14: 42555 | P14: 49500 | Q14: =ifna(index($U$6:$U$19,match(N14,$W$6:$W$19,0)),"") -> 0.3 | S14: =ifna(HLOOKUP(N14,AdvancedIndex!$X$5:$AA$7,3,false),"") | U14: 0.2 | W14: Wolfgang Ramjac
N15: Makai Bond | O15: 42312 | P15: 32500 | Q15: =ifna(index($U$6:$U$19,match(N15,$W$6:$W$19,0)),"") -> 0.2 | S15: =ifna(HLOOKUP(N15,AdvancedIndex!$X$5:$AA$7,3,false),"") | U15: 0.2 | W15: Paul Wells
N16: Paul Garza | O16: 42401 | P16: 34808 | Q16: =ifna(index($U$6:$U$19,match(N16,$W$6:$W$19,0)),"") | S16: =ifna(HLOOKUP(N16,AdvancedIndex!$X$5:$AA$7,3,false),"") | U16: 0.15 | W16: Robert Richardson
N17: Lamar Fry | O17: 42247 | P17: 36800 | Q17: =ifna(index($U$6:$U$19,match(N17,$W$6:$W$19,0)),"") | S17: =ifna(HLOOKUP(N17,AdvancedIndex!$X$5:$AA$7,3,false),"") | U17: 0.1 | W17: Walter Miller
N18: Natalie Porter | O18: 43500 | P18: 32100 | Q18: =ifna(index($U$6:$U$19,match(N18,$W$6:$W$19,0)),"") | S18: =ifna(HLOOKUP(N18,AdvancedIndex!$X$5:$AA$7,3,false),"") | U18: 0.1 | V18: Consider increasing | W18: Ewan Thompson
N19: Jim Mcguire | O19: 42541 | P19: 39600 | Q19: =ifna(index($U$6:$U$19,match(N19,$W$6:$W$19,0)),"") | S19: =ifna(HLOOKUP(N19,AdvancedIndex!$X$5:$AA$7,3,false),"") | U19: 0.1 | V19: Review after project | W19: Stevie Bridge
N20: Tommy Dixon | O20: 42649 | P20: 38500 | Q20: =ifna(index($U$6:$U$19,match(N20,$W$6:$W$19,0)),"") | S20: =ifna(HLOOKUP(N20,AdvancedIndex!$X$5:$AA$7,3,false),"")
N21: Robert Hurley | O21: 42877 | P21: 39400 | Q21: =ifna(index($U$6:$U$19,match(N21,$W$6:$W$19,0)),"") -> 0.25 | S21: =ifna(HLOOKUP(N21,AdvancedIndex!$X$5:$AA$7,3,false),"")
N22: Harry Burke | O22: 41841 | P22: 42500 | Q22: =ifna(index($U$6:$U$19,match(N22,$W$6:$W$19,0)),"") | S22: =ifna(HLOOKUP(N22,AdvancedIndex!$X$5:$AA$7,3,false),"")
N23: Robert Spear | O23: 42009 | P23: 43668 | Q23: =ifna(index($U$6:$U$19,match(N23,$W$6:$W$19,0)),"") | S23: =ifna(HLOOKUP(N23,AdvancedIndex!$X$5:$AA$7,3,false),"")
N24: Aydin Merritt | O24: 41582 | P24: 48500 | Q24: =ifna(index($U$6:$U$19,match(N24,$W$6:$W$19,0)),"") | S24: =ifna(HLOOKUP(N24,AdvancedIndex!$X$5:$AA$7,3,false),"")
N25: James Willard | O25: 41610 | P25: 49627 | Q25: =ifna(index($U$6:$U$19,match(N25,$W$6:$W$19,0)),"") | S25: =ifna(HLOOKUP(N25,AdvancedIndex!$X$5:$AA$7,3,false),"")
N26: Zac Fletcher | O26: 41470 | P26: 41200 | Q26: =ifna(index($U$6:$U$19,match(N26,$W$6:$W$19,0)),"") | S26: =ifna(HLOOKUP(N26,AdvancedIndex!$X$5:$AA$7,3,false),"")
N27: Kristina Mclean | O27: 41635 | P27: 52100 | Q27: =ifna(index($U$6:$U$19,match(N27,$W$6:$W$19,0)),"") -> 0.2 | S27: =ifna(HLOOKUP(N27,AdvancedIndex!$X$5:$AA$7,3,false),"")
N28: Maria Tot | O28: 42009 | P28: 88000 | Q28: =ifna(index($U$6:$U$19,match(N28,$W$6:$W$19,0)),"") | S28: =ifna(HLOOKUP(N28,AdvancedIndex!$X$5:$AA$7,3,false),"")
N29: Wolfgang Ramjac | O29: 37438 | P29: 116000 | Q29: =ifna(index($U$6:$U$19,match(N29,$W$6:$W$19,0)),"") -> 0.2 | S29: =ifna(HLOOKUP(N29,AdvancedIndex!$X$5:$AA$7,3,false),"")
N30: Peter Ramsy | O30: 40301 | P30: 65432 | Q30: =ifna(index($U$6:$U$19,match(N30,$W$6:$W$19,0)),"") | S30: =ifna(HLOOKUP(N30,AdvancedIndex!$X$5:$AA$7,3,false),"")
N31: Matilda Collier | O31: 41422 | P31: 65200 | Q31: =ifna(index($U$6:$U$19,match(N31,$W$6:$W$19,0)),"") | S31: =ifna(HLOOKUP(N31,AdvancedIndex!$X$5:$AA$7,3,false),"")
... N37: Robert Richardson | O37: 42675 | P37: 141200 | Q37: =ifna(index($U$6:$U$19,match(N37,$W$6:$W$19,0)),"") -> 0.15 | S37: =ifna(HLOOKUP(N37,AdvancedIndex!$X$5:$AA$7,3,false),"")

Sheet AdvancedIndex
A1: Index Match with Multiple Headers
B3: =B4&B5 -> JanuarySales | C3: =C4&C5 -> JanuaryQuantity | D3: =D4&D5 -> FebruarySales | E3: =E4&E5 -> FebruaryQuantity | F3: =F4&F5 -> MarchSales | G3: =G4&G5 -> MarchQuantity
B4: January | C4: January | D4: February | E4: February | F4: March | G4: March
B5: Sales | C5: Quantity | D5: Sales | E5: Quantity | F5: Sales | G5: Quantity
A6: Laptop | B6: 9150 | C6: 282 | D6: 8750 | E6: 270 | F6: 6840 | G6: 211 | J6: February
A7: Phone Case | B7: 10020 | C7: 142 | D7: 6220 | E7: 88 | F7: 9260 | G7: 131 | J7: Women
A8: Women | B8: 17500 | C8: 1458 | D8: 15000 | E8: 1250 | F8: 15800 | G8: 1317 | I8: Sales | J8: {=index(B6:G10,match(J7,A6:A10,0),match(J6&I8,B4:G4&B5:G5,0))} -> 15000
A9: Men | B9: 6620 | C9: 344 | D9: 6860 | E9: 356 | F9: 6050 | G9: 314
A10: Unisex | B10: 550 | C10: 92 | D10: 450 | E10: 75 | F10: 420 | G10: 70 | J10: {=index(B6:G10,match(J7,A6:A10,0),match(J6&I8,B3:G3,0))} -> 15000

Sheet Array Formulas
A1: Array Formulas | G1: --> | H1: Create Your Own Arrays
N2: Full name | O2: Salary | Q2: How many earn more than | R2: 25000
B3: Get Month Number | E3: Text length | H3: {={1,2,3;4,5,6}} -> 1 | I3: 2 | J3: 3 | L3: =iferror(FORMULATEXT(H3),"") -> ={1,2,3;4,5,6} | N3: Walter Miller | O3: 25709 | R3: =IFERROR(__xludf.DUMMYFUNCTION("{filter(N3:N12,O3:O12>R2);counta(filter(N3:N12,O3:O12>R2))}"),"Walter Miller") -> Walter Miller
A4: 44087 | B4: {=month(A4:A6)} -> 9 | D4: text 1 | E4: =len(D4) -> 6 | H4: 4 | I4: 5 | J4: 6 | N4: Kim West | O4: 26500 | R4: =IFERROR(__xludf.DUMMYFUNCTION("""COMPUTED_VALUE"""),"Kim West") -> Kim West
A5: 44390 | B5: 7 | D5: another text | E5: =len(D5) -> 12 | N5: Lyric Wise | O5: 24200 | R5: =IFERROR(__xludf.DUMMYFUNCTION("""COMPUTED_VALUE"""),"Vanessa Chavez") -> Vanessa Chavez
A6: 44482 | B6: 10 | D6: one more | E6: =len(D6) -> 8 | H6: {={{1,2,3};{4,5,6}}} -> 1 | I6: 2 | J6: 3 | L6: =iferror(FORMULATEXT(H6),"") -> ={{1,2,3};{4,5,6}} | N6: Vanessa Chavez | O6: 30600 | R6: =IFERROR(__xludf.DUMMYFUNCTION("""COMPUTED_VALUE"""),"Reid Good") -> Reid Good
D7: Total text length | E7: =sum(E4:E6) -> 26 | H7: 4 | I7: 5 | J7: 6 | N7: Reid Good | O7: 31900 | R7: =IFERROR(__xludf.DUMMYFUNCTION("""COMPUTED_VALUE"""),"Christopher Sharp") -> Christopher Sharp
D8: Total text length - array | E8: {=sum(len(D4:D6))} -> 26 | N8: Christopher Sharp | O8: 32500 | R8: =IFERROR(__xludf.DUMMYFUNCTION("""COMPUTED_VALUE"""),"Jessica Lowe") -> Jessica Lowe
A9: Use Arrays to Debug Functions | H9: {={1,4;2,5;3,6}} -> 1 | I9: 4 | L9: =iferror(FORMULATEXT(H9),"") -> ={1,4;2,5;3,6} | N9: Jessica Lowe | O9: 32800 | R9: =IFERROR(__xludf.DUMMYFUNCTION("""COMPUTED_VALUE"""),"Evie Williamson") -> Evie Williamson
H10: 2 | I10: 5 | N10: Evie Williamson | O10: 25900 | R10: =IFERROR(__xludf.DUMMYFUNCTION("""COMPUTED_VALUE"""),"Matilda Parry") -> Matilda Parry
A11: Full name | B11: Salary | E11: Who earns more than 30,000? | H11: 3 | I11: 6 | N11: Matilda Parry | O11: 49500 | R11: =IFERROR(__xludf.DUMMYFUNCTION("""COMPUTED_VALUE"""),"Makai Bond") -> Makai Bond
A12: Walter Miller | B12: 25709 | C12: {=B12:B21>30000} -> FALSE | E12: =IFERROR(__xludf.DUMMYFUNCTION("filter(A12:A21,B12:B21>30000)"),"Vanessa Chavez") -> Vanessa Chavez | N12: Makai Bond | O12: 32500 | R12: =IFERROR(__xludf.DUMMYFUNCTION("""COMPUTED_VALUE"""),9.0) -> 9
A13: Kim West | B13: 26500 | C13: FALSE | E13: =IFERROR(__xludf.DUMMYFUNCTION("""COMPUTED_VALUE"""),"Reid Good") -> Reid Good | H13: {={{1;2;3},{4;5;6}}} -> 1 | I13: 4 | L13: =iferror(FORMULATEXT(H13),"") -> ={{1;2;3},{4;5;6}}
A14: Lyric Wise | B14: 24200 | C14: FALSE | E14: =IFERROR(__xludf.DUMMYFUNCTION("""COMPUTED_VALUE"""),"Christopher Sharp") -> Christopher Sharp | H14: 2 | I14: 5
A15: Vanessa Chavez | B15: 30600 | C15: TRUE | E15: =IFERROR(__xludf.DUMMYFUNCTION("""COMPUTED_VALUE"""),"Jessica Lowe") -> Jessica Lowe | H15: 3 | I15: 6
A16: Reid Good | B16: 31900 | C16: TRUE | E16: =IFERROR(__xludf.DUMMYFUNCTION("""COMPUTED_VALUE"""),"Matilda Parry") -> Matilda Parry
A17: Christopher Sharp | B17: 32500 | C17: TRUE | E17: =IFERROR(__xludf.DUMMYFUNCTION("""COMPUTED_VALUE"""),"Makai Bond") -> Makai Bond | H17: Append Array Results
A18: Jessica Lowe | B18: 32800 | C18: TRUE | H18: =sum(H13:I15) -> 21 | I18: {={sum(H13:I15);count(H13:I15)}} -> 21
A19: Evie Williamson | B19: 25900 | C19: FALSE | H19: =count(H13:I15) -> 6 | I19: 6
A20: Matilda Parry | B20: 49500 | C20: TRUE
A21: Makai Bond | B21: 32500 | C21: TRUE

Sheet INDIRECT
A1: INDIRECT Function for More Flexibility
B3: Sales & Marketing
A4: Total Cost | B4: {=sum(indirect($B$3&"!C4:C50"))} -> 1074109
A5: Average Salary | B5: {=AVERAGE(indirect($B$3&"!C4:C50"))} -> 53705.45
A6: Median Salary | B6: {=MEDIAN(indirect($B$3&"!C4:C50"))} -> 40300

Sheet Sales & Marketing
A1: Sales & Marketing Department
A3: Name | B3: Position | C3: Salary
A4: Alissa Mitchell | B4: Marketing Analyst | C4: 25600
A5: Vanessa Chavez | B5: Marketing Assistant | C5: 30600
A6: Amber Stevens | B6: Project Manager | C6: 31200
A7: Matilda Parry | B7: Digital Marketing Manager | C7: 49500
A8: Jordan Parry | B8: Digital Marketing | C8: 58300
A9: Charlie Chambers | B9: Digital Marketing | C9: 36400
A10: Judy Bell | B10: Marketing Manager | C10: 79600
A11: Heidi Medina | B11: Projects Lead | C11: 56500
A12: Walter Miller | B12: Sales Assistant | C12: 25709
A13: Kim West | B13: Sales Assistant | C13: 26500
A14: Jessica Lowe | B14: Sales Representative | C14: 32800
A15: Evie Williamson | B15: Sales Representative | C15: 25900
... A23: Robert Richardson | B23: Head of Sales | C23: 141200

Sheet Finance
A1: Finance Department
A3: Name | B3: Position | C3: Salary
A4: Daniel Garrett | B4: Accountant | C4: 24700
A5: Skye Bennett | B5: Accountant | C5: 26900
A6: Braeden Wilkins | B6: Accountant | C6: 47200
A7: Donald Caldwell | B7: Financial Analyst | C7: 29800
A8: Richard Elliot | B8: Financial Analyst | C8: 49727
A9: Lukas Hofer | B9: Tax Analyst | C9: 49000
A10: Gary Miller | B10: Controller | C10: 65270
A11: Holly Macdonald | B11: Insurance Advisor | C11: 79600
A12: Crystal Doyle | B12: Finance Director | C12: 145000
A13: Imogen Clarke | B13: Tax Professional | C13: 86500
A14: Paul Hill | B14: Finance Manager | C14: 108357

Sheet Procurement
A1: Procurement Department
A3: Name | B3: Position | C3: Salary
A4: Ann Withers | B4: Procurement Assistant | C4: 23500
A5: Robert Marquez | B5: Buyer | C5: 26500
A6: Robert Musser | B6: Buyer | C6: 28400
A7: Matthew Ross | B7: Lead Buyer | C7: 59900
A8: Esme Carney | B8: Buyer | C8: 48500
A9: Tom Wood | B9: Lead Buyer | C9: 65200
A10: Betina Bauer | B10: Buyer | C10: 54600
A11: Cora Briggs | B11: Buyer | C11: 51300
A12: Mike Saban | B12: Category Manager | C12: 102500
A13: Corinna Schmidt | B13: Category Manager | C13: 86055
A14: Alex Collins | B14: Procurement Manager | C14: 142000

Sheet Random Data
A1: Generate Random Data & Text | O1: --> | P1: To Do
A2: 1. Without Functions | D2: 2. With Functions | J2: 3. No Repetitions (Randomly assign names to teams) | P2: Create 10 rows of random dates from 1st of March 2020 to 1st of June 2020
C3: FALSE
A4: Numbers | B4: Text | D4: RAND | E4: RANDBETWEEN | F4: RANDARRAY | G4: Random Division | H4: Utility | J4: Team | K4: Name | M4: Name | P4: =RANDBETWEEN("3/1/2020","6/1/2020") -> 43919
A5: 8 | B5: Productivity | D5: =rand() -> 0.29157178 | E5: =RANDBETWEEN(100,1000) -> 475 | F5: {=RANDARRAY(10)} -> 0.30634234 | G5: =index($H$4:$H$6,randbetween(1,3)) -> Productivity | H5: Productivity | J5: A | K5: {=sort(M5:M24,RANDARRAY(20),true)} -> Stevens A | M5: Bell J | P5: =RANDBETWEEN("3/1/2020","6/1/2020") -> 43953
A6: 15 | B6: Game | E6: =RANDBETWEEN(100,1000) -> 997 | F6: 0.66721228 | G6: =index($H$4:$H$6,randbetween(1,3)) -> Productivity | H6: Game | J6: A | K6: Miller W | M6: Bond B | P6: =RANDBETWEEN("3/1/2020","6/1/2020") -> 43961
A7: 7 | B7: Utility | E7: =RANDBETWEEN(100,1000) -> 221 | F7: 0.59842012 | G7: =index($H$4:$H$6,randbetween(1,3)) -> Productivity | J7: A | K7: Bridge S | M7: Bridge S | P7: =RANDBETWEEN("3/1/2020","6/1/2020") -> 43923
A8: 11 | B8: Game | E8: =RANDBETWEEN(100,1000) -> 779 | F8: 0.78784909 | G8: =index($H$4:$H$6,randbetween(1,3)) -> Productivity | J8: A | K8: Mclean K | M8: Burke H | P8: =RANDBETWEEN("3/1/2020","6/1/2020") -> 43948
A9: 13 | B9: Utility | E9: =RANDBETWEEN(100,1000) -> 270 | F9: 0.32075065 | G9: =index($H$4:$H$6,randbetween(1,3)) -> Game | J9: A | K9: Lowe J | M9: Chambers C | P9: =RANDBETWEEN("3/1/2020","6/1/2020") -> 43892
A10: 1 | B10: Game | E10: =RANDBETWEEN(100,1000) -> 767 | F10: 0.32104727 | G10: =index($H$4:$H$6,randbetween(1,3)) -> Utility | J10: B | K10: Fletcher Z | M10: Chavez V | P10: =RANDBETWEEN("3/1/2020","6/1/2020") -> 43939
A11: 14 | B11: Utility | E11: =RANDBETWEEN(100,1000) -> 564 | F11: 0.18640792 | G11: =index($H$4:$H$6,randbetween(1,3)) -> Productivity | J11: B | K11: Williamson E | M11: Dixon T | P11: =RANDBETWEEN("3/1/2020","6/1/2020") -> 43956
A12: 5 | B12: Utility | E12: =RANDBETWEEN(100,1000) -> 763 | F12: 0.17640205 | G12: =index($H$4:$H$6,randbetween(1,3)) -> Utility | J12: B | K12: Mitchell A | M12: Fletcher Z | P12: =RANDBETWEEN("3/1/2020","6/1/2020") -> 43902
A13: 4 | B13: Productivity | E13: =RANDBETWEEN(100,1000) -> 586 | F13: 0.32155684 | G13: =index($H$4:$H$6,randbetween(1,3)) -> Productivity | J13: B | K13: West K | M13: Hurley R | P13: =RANDBETWEEN("3/1/2020","6/1/2020") -> 43976
A14: 10 | B14: Game | E14: =RANDBETWEEN(100,1000) -> 838 | F14: 0.79317812 | G14: =index($H$4:$H$6,randbetween(1,3)) -> Productivity | J14: B | K14: Bond B | M14: Lowe J
A15: 6 | B15: Utility | J15: C | K15: Bell J | M15: Mclean K
A16: 12 | B16: Productivity | J16: C | K16: Parry J | M16: Medina H
A17: 2 | B17: Game | J17: C | K17: Dixon T | M17: Miller W
A18: 3 | B18: Productivity | J18: C | K18: Richardson R | M18: Mitchell A
A19: 9 | B19: Productivity | J19: C | K19: Chambers C | M19: Parry J
J20: D | K20: Chavez V | M20: Parry M
J21: D | K21: Burke H | M21: Richardson R
J22: D | K22: Hurley R | M22: Stevens A
J23: D | K23: Parry M | M23: West K
J24: D | K24: Medina H | M24: Williamson E

Sheet SEQUENCE
A1: The Power of the Sequence Function | H1: -->
M2: 2020
A3: Basics
A4: {=SEQUENCE(2,3,1,1)} -> 1 | B4: 2 | C4: 3 | E4: {=SEQUENCE(5,1,"9/1/2020",7)} -> 44075 | K4: Sun | L4: Mon | M4: Tue | N4: Wed | O4: Thu | P4: Fri | Q4: Sat
A5: 4 | B5: 5 | C5: 6 | E5: 44082 | K5: {=sequence(53,7,date($M$2,1,1)- WEEKDAY(date($M$2,1,1))+1,1)} -> 43828 | L5: 43829 | M5: 43830 | N5: 43831 | O5: 43832 | P5: 43833 | Q5: 43834
E6: 44089 | K6: 43835 | L6: 43836 | M6: 43837 | N6: 43838 | O6: 43839 | P6: 43840 | Q6: 43841
A7: {=transpose(SEQUENCE(2,3,1,1))} -> 1 | B7: 4 | E7: 44096 | K7: 43842 | L7: 43843 | M7: 43844 | N7: 43845 | O7: 43846 | P7: 43847 | Q7: 43848
A8: 2 | B8: 5 | E8: 44103 | K8: 43849 | L8: 43850 | M8: 43851 | N8: 43852 | O8: 43853 | P8: 43854 | Q8: 43855
A9: 3 | B9: 6 | K9: 43856 | L9: 43857 | M9: 43858 | N9: 43859 | O9: 43860 | P9: 43861 | Q9: 43862
K10: 43863 | L10: 43864 | M10: 43865 | N10: 43866 | O10: 43867 | P10: 43868 | Q10: 43869
A11: SEQUENCE For Dynamic Indexing | K11: 43870 | L11: 43871 | M11: 43872 | N11: 43873 | O11: 43874 | P11: 43875 | Q11: 43876
K12: 43877 | L12: 43878 | M12: 43879 | N12: 43880 | O12: 43881 | P12: 43882 | Q12: 43883
A13: Full name | B13: Salary | D13: How many earn more than | E13: 20000 | K13: 43884 | L13: 43885 | M13: 43886 | N13: 43887 | O13: 43888 | P13: 43889 | Q13: 43890
A14: Walter Miller | B14: 25709 | D14: {=SEQUENCE(counta(E14:E29),1)} -> 1 | E14: =IFERROR(__xludf.DUMMYFUNCTION("filter(A14:A23,B14:B23>E13)"),"Walter Miller") -> Walter Miller | K14: 43891 | L14: 43892 | M14: 43893 | N14: 43894 | O14: 43895 | P14: 43896 | Q14: 43897
A15: Kim West | B15: 26500 | D15: 2 | E15: =IFERROR(__xludf.DUMMYFUNCTION("""COMPUTED_VALUE"""),"Kim West") -> Kim West | K15: 43898 | L15: 43899 | M15: 43900 | N15: 43901 | O15: 43902 | P15: 43903 | Q15: 43904
A16: Lyric Wise | B16: 24200 | D16: 3 | E16: =IFERROR(__xludf.DUMMYFUNCTION("""COMPUTED_VALUE"""),"Lyric Wise") -> Lyric Wise | K16: 43905 | L16: 43906 | M16: 43907 | N16: 43908 | O16: 43909 | P16: 43910 | Q16: 43911
A17: Vanessa Chavez | B17: 30600 | D17: 4 | E17: =IFERROR(__xludf.DUMMYFUNCTION("""COMPUTED_VALUE"""),"Vanessa Chavez") -> Vanessa Chavez | K17: 43912 | L17: 43913 | M17: 43914 | N17: 43915 | O17: 43916 | P17: 43917 | Q17: 43918
A18: Reid Good | B18: 31900 | D18: 5 | E18: =IFERROR(__xludf.DUMMYFUNCTION("""COMPUTED_VALUE"""),"Reid Good") -> Reid Good | K18: 43919 | L18: 43920 | M18: 43921 | N18: 43922 | O18: 43923 | P18: 43924 | Q18: 43925
A19: Christopher Sharp | B19: 32500 | D19: 6 | E19: =IFERROR(__xludf.DUMMYFUNCTION("""COMPUTED_VALUE"""),"Christopher Sharp") -> Christopher Sharp | K19: 43926 | L19: 43927 | M19: 43928 | N19: 43929 | O19: 43930 | P19: 43931 | Q19: 43932
A20: Jessica Lowe | B20: 32800 | D20: 7 | E20: =IFERROR(__xludf.DUMMYFUNCTION("""COMPUTED_VALUE"""),"Jessica Lowe") -> Jessica Lowe | K20: 43933 | L20: 43934 | M20: 43935 | N20: 43936 | O20: 43937 | P20: 43938 | Q20: 43939
A21: Evie Williamson | B21: 25900 | D21: 8 | E21: =IFERROR(__xludf.DUMMYFUNCTION("""COMPUTED_VALUE"""),"Evie Williamson") -> Evie Williamson | K21: 43940 | L21: 43941 | M21: 43942 | N21: 43943 | O21: 43944 | P21: 43945 | Q21: 43946
A22: Matilda Parry | B22: 49500 | D22: 9 | E22: =IFERROR(__xludf.DUMMYFUNCTION("""COMPUTED_VALUE"""),"Matilda Parry") -> Matilda Parry | K22: 43947 | L22: 43948 | M22: 43949 | N22: 43950 | O22: 43951 | P22: 43952 | Q22: 43953
A23: Makai Bond | B23: 32500 | D23: 10 | E23: =IFERROR(__xludf.DUMMYFUNCTION("""COMPUTED_VALUE"""),"Makai Bond") -> Makai Bond | K23: 43954 | L23: 43955 | M23: 43956 | N23: 43957 | O23: 43958 | P23: 43959 | Q23: 43960
K24: 43961 | L24: 43962 | M24: 43963 | N24: 43964 | O24: 43965 | P24: 43966 | Q24: 43967
K25: 43968 | L25: 43969 | M25: 43970 | N25: 43971 | O25: 43972 | P25: 43973 | Q25: 43974
K26: 43975 | L26: 43976 | M26: 43977 | N26: 43978 | O26: 43979 | P26: 43980 | Q26: 43981
K27: 43982 | L27: 43983 | M27: 43984 | N27: 43985 | O27: 43986 | P27: 43987 | Q27: 43988
K28: 43989 | L28: 43990 | M28: 43991 | N28: 43992 | O28: 43993 | P28: 43994 | Q28: 43995
K29: 43996 | L29: 43997 | M29: 43998 | N29: 43999 | O29: 44000 | P29: 44001 | Q29: 44002
K30: 44003 | L30: 44004 | M30: 44005 | N30: 44006 | O30: 44007 | P30: 44008 | Q30: 44009
K31: 44010 | L31: 44011 | M31: 44012 | N31: 44013 | O31: 44014 | P31: 44015 | Q31: 44016
K32: 44017 | L32: 44018 | M32: 44019 | N32: 44020 | O32: 44021 | P32: 44022 | Q32: 44023
K33: 44024 | L33: 44025 | M33: 44026 | N33: 44027 | O33: 44028 | P33: 44029 | Q33: 44030
K34: 44031 | L34: 44032 | M34: 44033 | N34: 44034 | O34: 44035 | P34: 44036 | Q34: 44037
K35: 44038 | L35: 44039 | M35: 44040 | N35: 44041 | O35: 44042 | P35: 44043 | Q35: 44044
... K57: 44192 | L57: 44193 | M57: 44194 | N57: 44195 | O57: 44196 | P57: 44197 | Q57: 44198
